logger_util/__init__.py
logger_util/logger_util.py
logger_util-0.3.0.dist-info/LICENSE
logger_util-0.3.0.dist-info/METADATA
logger_util-0.3.0.dist-info/WHEEL
logger_util-0.3.0.dist-info/top_level.txt
logger_util-0.3.0.dist-info/RECORD
