Metadata-Version: 2.1
Name: logger-util
Version: 0.3.0
Summary: Dead simple Python logger. Redirects stdout to a file while maintaining console printing.
Home-page: https://github.com/wsarce/logger-util
Author: Walker Arce (wsarce)
Author-email: wsarcera@gmail.com
License: MIT
Keywords: logger_util logging python wsarce
Classifier: License :: OSI Approved :: MIT License
Classifier: Programming Language :: Python :: 3.8
License-File: LICENSE
Requires-Dist: wmi
